[
  {
    "id": "ZTE Open C FR (developer image)",
    "adb": {
      "ro.product.name": "ZTE_OPENC",
      "ro.product.device": "ZTE_P821A10",
      "ro.product.manufacturer": "ZTE",
      "ro.build.id": "JLS36C",
      "ro.build.type": "eng",
      "ro.build.inner.version": "FFOS_FR_ZTE_P821A10V1.0.0B02",
      "ro.build.version.incremental": "eng..20140806.064432"
    },
    "fastboot": {
      "product": [ "MSM8610" ],
      "version": [ "0.5" ]
    }
  },
  {
    "id": "ZTE Open C FR (community build)",
    "adb": {
      "ro.product.name": "zte_openc_fr",
      "ro.product.device": "zte_p821a10",
      "ro.product.manufacturer": "ZTE",
      "ro.build.type": [ "eng", "userdebug" ]
    },
    "fastboot": {
      "product": [ "MSM8610" ],
      "version": [ "0.5" ]
    }
  }
]
